[
  {
    "billing_id": "BILL-0001",
    "customer_id": "CUST-001",
    "customer_name": "Greenwood Furniture Co.",
    "invoice_number": "INV-1001",
    "invoice_date": "2025-08-01",
    "due_date": "2025-08-15",
    "status": "Paid",
    "total_amount": 520000,
    "currency": "USD",
    "tax_amount": 78000,
    "discount_amount": 60000,
    "created_by": "billing_user_01",
    "created_at": "2025-08-01T09:00:00Z"
  },
  {
    "billing_id": "BILL-0002",
    "customer_id": "CUST-002",
    "customer_name": "BlueTech Electronics",
    "invoice_number": "INV-1002",
    "invoice_date": "2025-08-02",
    "due_date": "2025-08-16",
    "status": "Unpaid",
    "total_amount": 345000,
    "currency": "USD",
    "tax_amount": 51750,
    "discount_amount": 50100,
    "created_by": "billing_user_02",
    "created_at": "2025-08-02T10:15:00Z"
  },
  {
    "billing_id": "BILL-0003",
    "customer_id": "CUST-003",
    "customer_name": "Modern Workspace Ltd.",
    "invoice_number": "INV-1003",
    "invoice_date": "2025-08-03",
    "due_date": "2025-08-17",
    "status": "Overdue",
    "total_amount": 610000,
    "currency": "USD",
    "tax_amount": 91500,
    "discount_amount": 0,
    "created_by": "billing_user_03",
    "created_at": "2025-08-03T11:30:00Z"
  },
  {
    "billing_id": "BILL-0004",
    "customer_id": "CUST-004",
    "customer_name": "City Office Supplies",
    "invoice_number": "INV-1004",
    "invoice_date": "2025-08-04",
    "due_date": "2025-08-18",
    "status": "Paid",
    "total_amount": 280000,
    "currency": "USD",
    "tax_amount": 42000,
    "discount_amount": 0,
    "created_by": "billing_user_01",
    "created_at": "2025-08-04T08:45:00Z"
  },
  {
    "billing_id": "BILL-0005",
    "customer_id": "CUST-005",
    "customer_name": "EcoSmart Systems",
    "invoice_number": "INV-1005",
    "invoice_date": "2025-08-05",
    "due_date": "2025-08-20",
    "status": "Cancelled",
    "total_amount": 395000,
    "currency": "USD",
    "tax_amount": 59200,
    "discount_amount": 90000,
    "created_by": "billing_user_02",
    "created_at": "2025-08-05T12:00:00Z"
  },
  {
    "billing_id": "BILL-0006",
    "customer_id": "CUST-006",
    "customer_name": "Future Homes Inc.",
    "invoice_number": "INV-1006",
    "invoice_date": "2025-08-06",
    "due_date": "2025-08-21",
    "status": "Unpaid",
    "total_amount": 720000,
    "currency": "USD",
    "tax_amount": 108000,
    "discount_amount": 15000,
    "created_by": "billing_user_03",
    "created_at": "2025-08-06T14:20:00Z"
  },
  {
    "billing_id": "BILL-0007",
    "customer_id": "CUST-001",
    "customer_name": "Greenwood Furniture Co.",
    "invoice_number": "INV-1007",
    "invoice_date": "2025-08-07",
    "due_date": "2025-08-22",
    "status": "Paid",
    "total_amount": 210000,
    "currency": "USD",
    "tax_amount": 31500,
    "discount_amount": 25999,
    "created_by": "billing_user_01",
    "created_at": "2025-08-07T10:30:00Z"
  },
  {
    "billing_id": "BILL-0008",
    "customer_id": "CUST-002",
    "customer_name": "BlueTech Electronics",
    "invoice_number": "INV-1008",
    "invoice_date": "2025-08-08",
    "due_date": "2025-08-23",
    "status": "Unpaid",
    "total_amount": 465000,
    "currency": "USD",
    "tax_amount": 69700,
    "discount_amount": 0,
    "created_by": "billing_user_02",
    "created_at": "2025-08-08T09:00:00Z"
  },
  {
    "billing_id": "BILL-0009",
    "customer_id": "CUST-003",
    "customer_name": "Modern Workspace Ltd.",
    "invoice_number": "INV-1009",
    "invoice_date": "2025-08-09",
    "due_date": "2025-08-24",
    "status": "Overdue",
    "total_amount": 350000,
    "currency": "USD",
    "tax_amount": 52500,
    "discount_amount": 50999,
    "created_by": "billing_user_03",
    "created_at": "2025-08-09T15:30:00Z"
  },
  {
    "billing_id": "BILL-0010",
    "customer_id": "CUST-004",
    "customer_name": "City Office Supplies",
    "invoice_number": "INV-1010",
    "invoice_date": "2025-08-10",
    "due_date": "2025-08-25",
    "status": "Paid",
    "total_amount": 130000,
    "currency": "USD",
    "tax_amount": 19500,
    "discount_amount": 20345,
    "created_by": "billing_user_01",
    "created_at": "2025-08-10T10:45:00Z"
  },
  {
    "billing_id": "BILL-0011",
    "customer_id": "CUST-005",
    "customer_name": "EcoSmart Systems",
    "invoice_number": "INV-1011",
    "invoice_date": "2025-08-11",
    "due_date": "2025-08-26",
    "status": "Unpaid",
    "total_amount": 590000,
    "currency": "USD",
    "tax_amount": 88500,
    "discount_amount": 0,
    "created_by": "billing_user_02",
    "created_at": "2025-08-11T13:20:00Z"
  },
  {
    "billing_id": "BILL-0012",
    "customer_id": "CUST-006",
    "customer_name": "Future Homes Inc.",
    "invoice_number": "INV-1012",
    "invoice_date": "2025-08-12",
    "due_date": "2025-08-27",
    "status": "Paid",
    "total_amount": 800000,
    "currency": "USD",
    "tax_amount": 120000,
    "discount_amount": 20099,
    "created_by": "billing_user_03",
    "created_at": "2025-08-12T11:50:00Z"
  },
  {
    "billing_id": "BILL-0013",
    "customer_id": "CUST-007",
    "customer_name": "Urban Living Corp.",
    "invoice_number": "INV-1013",
    "invoice_date": "2025-08-13",
    "due_date": "2025-08-28",
    "status": "Cancelled",
    "total_amount": 440000,
    "currency": "USD",
    "tax_amount": 66000,
    "discount_amount": 0,
    "created_by": "billing_user_01",
    "created_at": "2025-08-13T16:30:00Z"
  },
  {
    "billing_id": "BILL-0014",
    "customer_id": "CUST-008",
    "customer_name": "NovaBuild Solutions",
    "invoice_number": "INV-1014",
    "invoice_date": "2025-08-14",
    "due_date": "2025-08-29",
    "status": "Paid",
    "total_amount": 900000,
    "currency": "USD",
    "tax_amount": 135000,
    "discount_amount": 12500,
    "created_by": "billing_user_02",
    "created_at": "2025-08-14T10:10:00Z"
  },
  {
    "billing_id": "BILL-0015",
    "customer_id": "CUST-009",
    "customer_name": "DesignEra Interiors",
    "invoice_number": "INV-1015",
    "invoice_date": "2025-08-15",
    "due_date": "2025-08-30",
    "status": "Unpaid",
    "total_amount": 315000,
    "currency": "USD",
    "tax_amount": 47200,
    "discount_amount": 0,
    "created_by": "billing_user_03",
    "created_at": "2025-08-15T14:00:00Z"
  },
  {
    "billing_id": "BILL-0016",
    "customer_id": "CUST-010",
    "customer_name": "Zenith Innovations",
    "invoice_number": "INV-1016",
    "invoice_date": "2025-08-16",
    "due_date": "2025-08-31",
    "status": "Paid",
    "total_amount": 275000,
    "currency": "USD",
    "tax_amount": 41200,
    "discount_amount": 35000,
    "created_by": "billing_user_01",
    "created_at": "2025-08-16T12:40:00Z"
  },
  {
    "billing_id": "BILL-0017",
    "customer_id": "CUST-001",
    "customer_name": "Greenwood Furniture Co.",
    "invoice_number": "INV-1017",
    "invoice_date": "2025-08-17",
    "due_date": "2025-09-01",
    "status": "Unpaid",
    "total_amount": 400000,
    "currency": "USD",
    "tax_amount": 60000,
    "discount_amount": 0,
    "created_by": "billing_user_02",
    "created_at": "2025-08-17T13:50:00Z"
  },
  {
    "billing_id": "BILL-0018",
    "customer_id": "CUST-003",
    "customer_name": "Modern Workspace Ltd.",
    "invoice_number": "INV-1018",
    "invoice_date": "2025-08-18",
    "due_date": "2025-09-02",
    "status": "Paid",
    "total_amount": 850000,
    "currency": "USD",
    "tax_amount": 127500,
    "discount_amount": 10890,
    "created_by": "billing_user_03",
    "created_at": "2025-08-18T11:20:00Z"
  },
  {
    "billing_id": "BILL-0019",
    "customer_id": "CUST-004",
    "customer_name": "City Office Supplies",
    "invoice_number": "INV-1019",
    "invoice_date": "2025-08-19",
    "due_date": "2025-09-03",
    "status": "Unpaid",
    "total_amount": 390000,
    "currency": "USD",
    "tax_amount": 58500,
    "discount_amount": 0,
    "created_by": "billing_user_01",
    "created_at": "2025-08-19T09:40:00Z"
  },
  {
    "billing_id": "BILL-0020",
    "customer_id": "CUST-002",
    "customer_name": "BlueTech Electronics",
    "invoice_number": "INV-1020",
    "invoice_date": "2025-08-20",
    "due_date": "2025-09-04",
    "status": "Cancelled",
    "total_amount": 250000,
    "currency": "USD",
    "tax_amount": 37500,
    "discount_amount": 0,
    "created_by": "billing_user_02",
    "created_at": "2025-08-20T10:55:00Z"
  }
]
